jsnlog/__init__.py
jsnlog/apps.py
jsnlog/urls.py
jsnlog/views.py
jsnlog/static/jsnlog/js/django-jsnlog.js
jsnlog/static/jsnlog/js/jsnlog.min.js
django_jsnlog-0.4.0.dist-info/AUTHORS.rst
django_jsnlog-0.4.0.dist-info/LICENSE
django_jsnlog-0.4.0.dist-info/METADATA
django_jsnlog-0.4.0.dist-info/WHEEL
django_jsnlog-0.4.0.dist-info/top_level.txt
django_jsnlog-0.4.0.dist-info/RECORD
