Metadata-Version: 2.1
Name: django-jsnlog
Version: 0.4.0
Summary: A Django app to integrate client side javascript logging with JSNLog.
Home-page: https://github.com/oruehenbeck/django-jsnlog
Author: Tobias Funke
Author-email: tfunke@bona-fide.it
License: MIT
Keywords: django-jsnlog
Classifier: Development Status :: 3 - Alpha
Classifier: Framework :: Django :: 3.2
Classifier: Framework :: Django :: 4.2
Classifier: Framework :: Django :: 5.0
Classifier: Intended Audience :: Developers
Classifier: License :: OSI Approved :: BSD License
Classifier: Natural Language :: English
Classifier: Programming Language :: Python :: 3
Classifier: Programming Language :: Python :: 3.8
Classifier: Programming Language :: Python :: 3.9
Classifier: Programming Language :: Python :: 3.10
Classifier: Programming Language :: Python :: 3.11
License-File: LICENSE
License-File: AUTHORS.rst
Requires-Dist: Django >=3.2
